powcaptcha/captcha.py
powcaptcha/utils.py
powcaptcha/__init__.py
powcaptcha-0.2.0.dist-info/WHEEL
powcaptcha-0.2.0.dist-info/entry_points.txt
powcaptcha-0.2.0.dist-info/METADATA
powcaptcha-0.2.0.dist-info/RECORD
